lingua_py_unofficial-0.1.2.dist-info/METADATA
lingua_py_unofficial-0.1.2.dist-info/WHEEL
lingua_py_unofficial-0.1.2.dist-info/license_files/LICENSE
lingua_py/__init__.py
lingua_py/lingua_py.pyd
lingua_py_unofficial-0.1.2.dist-info/RECORD
