Metadata-Version: 2.1
Name: lingua-py-unofficial
Version: 0.1.2
Classifier: Programming Language :: Rust
Classifier: Programming Language :: Python :: Implementation :: CPython
Classifier: Programming Language :: Python :: Implementation :: PyPy
Classifier: License :: OSI Approved :: Apache Software License
License-File: LICENSE
Summary: Python bindings for the Lingua(LanguageDetect) Rust library
Keywords: nlp,language-detect,rust,rust-library,python-bindings
Author-email: chatblanc <73688885+chatblanc-ciel@users.noreply.github.com>
Requires-Python: >=3.11, <3.12
Project-URL: Repository, https://github.com/chatblanc-ciel/lingua-py.git
